[
  {
    "name": "Altair",
    "x": 1.8,
    "y": 0.9,
    "z": -0.5,
    "dist": 16.7,
    "type": "A7V",
    "ra": 297.6958,
    "dec": 8.8683,
    "temperature": 7550,
    "radius": 1.8,
    "mass": 1.8,
    "luminosity": 10.6,
    "exoplanets": [],
    "description": "Altair races through space with astonishing speed, spinning so fast it bulges at its equator. In the myth of the Weaver and the Cowherd, Altair stands as the separated lover across the river of stars, waiting for the single night each year when the bridge of magpies forms."
  },
  {
    "name": "Deneb",
    "x": -2.5,
    "y": 1.2,
    "z": 0.6,
    "dist": 2615,
    "type": "A2Ia",
    "ra": 310.3579,
    "dec": 45.2803,
    "temperature": 8525,
    "radius": 203,
    "mass": 19,
    "luminosity": 196000,
    "exoplanets": [],
    "description": "Deneb is a luminous supergiant — one of the most distant stars visible to the naked eye. In the ancient skies of the Middle East, it was the tail of the celestial swan flying along the Milky Way, guiding souls across the river of night."
  },
  {
    "name": "Spica",
    "x": 2.2,
    "y": -1.1,
    "z": 0.3,
    "dist": 250,
    "type": "B1III-IV",
    "ra": 201.2983,
    "dec": -11.1614,
    "temperature": 22400,
    "radius": 7.4,
    "mass": 10.25,
    "luminosity": 22000,
    "exoplanets": [],
    "description": "Spica is a blazing blue-white binary, its components locked in a close gravitational embrace. In antiquity, it symbolized the ear of wheat in the hand of Virgo, marking the rhythm of harvests and the returning cycle of life."
  },
  {
    "name": "Antares",
    "x": -2.8,
    "y": -0.4,
    "z": 1.2,
    "dist": 550,
    "type": "M1.5Iab-Ib",
    "ra": 247.3519,
    "dec": -26.4320,
    "temperature": 3500,
    "radius": 680,
    "mass": 11,
    "luminosity": 100000,
    "exoplanets": [],
    "description": "Antares glows like a smoldering coal in the heart of Scorpio. Its ancient name means 'rival of Mars,' for the two once fought for dominance in the night. It is a dying supergiant — vast, unstable, and magnificent."
  },
  {
    "name": "Fomalhaut",
    "x": 1.4,
    "y": 1.7,
    "z": -1.0,
    "dist": 25.1,
    "type": "A3V",
    "ra": 344.4128,
    "dec": -29.6222,
    "temperature": 8590,
    "radius": 1.8,
    "mass": 1.9,
    "luminosity": 16.6,
    "exoplanets": ["Fomalhaut b"],
    "description": "Known as the 'Lonely Star' of the southern sky, Fomalhaut shines alone in a wide expanse of darkness. Surrounded by a great ring of dust, it is the eye of the celestial fish in ancient Arabian star-lore."
  },
  {
    "name": "Aldebaran",
    "x": -1.6,
    "y": 0.7,
    "z": -1.3,
    "dist": 65.3,
    "type": "K5III",
    "ra": 68.9800,
    "dec": 16.5093,
    "temperature": 3910,
    "radius": 44.2,
    "mass": 1.16,
    "luminosity": 518,
    "exoplanets": ["Aldebaran b"],
    "description": "Aldebaran burns with a steady copper flame, the eye of Taurus the Bull. Many cultures saw it as a watchful guardian of the winter sky, overseeing the passage of seasons and the migrations of people and stars alike."
  },
  {
    "name": "Regulus",
    "x": 1.9,
    "y": -0.8,
    "z": -0.9,
    "dist": 79.3,
    "type": "B7V",
    "ra": 152.0929,
    "dec": 11.9672,
    "temperature": 12460,
    "radius": 3.8,
    "mass": 3.8,
    "luminosity": 288,
    "exoplanets": [],
    "description": "Regulus is the heart of the Lion — Leo — bright and regal. It spins so rapidly that it bulges at the equator, a crown of fire stretched thin by its own motion. In Persian astronomy, it was one of the Four Royal Stars of Heaven."
  },
  {
    "name": "Pollux",
    "x": -1.0,
    "y": 1.3,
    "z": 0.3,
    "dist": 33.8,
    "type": "K0III",
    "ra": 113.6494,
    "dec": 28.0262,
    "temperature": 4865,
    "radius": 8.8,
    "mass": 1.9,
    "luminosity": 32,
    "exoplanets": ["Pollux b"],
    "description": "Pollux burns with warm golden light and hosts a giant planet. In myth, Pollux was the immortal brother — a light that remains after all else fades."
  },
  {
    "name": "Castor",
    "x": 1.3,
    "y": 1.1,
    "z": 1.3,
    "dist": 51.6,
    "type": "A1V",
    "ra": 113.2156,
    "dec": 27.9770,
    "temperature": 10200,
    "radius": 2.4,
    "mass": 2.1,
    "luminosity": 14,
    "exoplanets": [],
    "description": "Castor is not one star, but six — a gravitational family bound in luminous choreography. It is the mortal brother in myth, brilliant yet destined to fade."
  },
  {
    "name": "Procyon",
    "x": -0.8,
    "y": -1.4,
    "z": 0.4,
    "dist": 11.46,
    "type": "F5IV-V",
    "ra": 114.8255,
    "dec": 5.2249,
    "temperature": 6530,
    "radius": 2.0,
    "mass": 1.5,
    "luminosity": 6.9,
    "exoplanets": [],
    "description": "Procyon rises before Sirius, heralding the coming of the great winter star. It has a faint white dwarf companion — the burned-out core of a sun that once shone bright."
  },

  {
    "name": "Capella",
    "x": 2.4,
    "y": 0.2,
    "z": 1.5,
    "dist": 43.0,
    "type": "G8III",
    "ra": 79.1723,
    "dec": 45.9979,
    "temperature": 4970,
    "radius": 11.9,
    "mass": 2.5,
    "luminosity": 78,
    "exoplanets": [],
    "description": "Capella is a pair of giant suns locked in a slow and dignified orbit. In ancient Greece it represented Amalthea, the celestial goat who nourished Zeus — a light of protection and nurturing grace."
  },
  {
    "name": "Bellatrix",
    "x": -1.9,
    "y": 2.4,
    "z": -0.4,
    "dist": 246,
    "type": "B2III",
    "ra": 81.2828,
    "dec": 6.3497,
    "temperature": 21900,
    "radius": 5.8,
    "mass": 8.6,
    "luminosity": 6000,
    "exoplanets": [],
    "description": "Bellatrix is the Amazon Star — the Warrior of Orion. Though smaller than Rigel or Betelgeuse, it shines with fierce clarity, a beacon of courage in the celestial hunt."
  },
  {
    "name": "Saiph",
    "x": -2.3,
    "y": -1.5,
    "z": 1.0,
    "dist": 650,
    "type": "B0.5Ia",
    "ra": 86.9391,
    "dec": -9.6696,
    "temperature": 26500,
    "radius": 22,
    "mass": 15,
    "luminosity": 57500,
    "exoplanets": [],
    "description": "Saiph marks Orion’s knee — a blue-white blaze of intense heat. Its brilliance masks a truth: much of its light lies in wavelengths the human eye cannot see, burning beyond sight."
  },
  {
    "name": "Dubhe",
    "x": 1.6,
    "y": -2.2,
    "z": -0.3,
    "dist": 123,
    "type": "K0III",
    "ra": 165.460,
    "dec": 61.750,
    "temperature": 4665,
    "radius": 30,
    "mass": 4.25,
    "luminosity": 300,
    "exoplanets": [],
    "description": "Dubhe is one of the two pointer stars guiding navigators to Polaris. It has served travelers for centuries, a steady flame in the turning wheel of the night."
  },
  {
    "name": "Merak",
    "x": -1.4,
    "y": -2.0,
    "z": -0.6,
    "dist": 79.7,
    "type": "A1V",
    "ra": 165.932,
    "dec": 56.383,
    "temperature": 9330,
    "radius": 2.7,
    "mass": 2.4,
    "luminosity": 35,
    "exoplanets": [],
    "description": "Merak stands with Dubhe as a guidepost in the sky, pointing the way to true north. Together they mark the bowl of the Big Dipper — a celestial map etched in light."
  },
  {
    "name": "Mizar",
    "x": -2.2,
    "y": 0.8,
    "z": -1.2,
    "dist": 83.2,
    "type": "A2V",
    "ra": 200.9814,
    "dec": 54.9254,
    "temperature": 9000,
    "radius": 2.4,
    "mass": 2.0,
    "luminosity": 34,
    "exoplanets": [],
    "description": "Mizar and Alcor are the ancient eye test of the desert caravans — two lights so close that the sharp-eyed could distinguish them. Today we know Mizar is itself multiple stars entwined."
  },
  {
    "name": "Alcor",
    "x": -2.1,
    "y": 1.0,
    "z": -1.3,
    "dist": 81.7,
    "type": "A5V",
    "ra": 201.3063,
    "dec": 54.9879,
    "temperature": 8200,
    "radius": 1.9,
    "mass": 1.9,
    "luminosity": 12,
    "exoplanets": [],
    "description": "Alcor travels beside Mizar across the heavens. In many cultures, the ability to see the pair marked keen vision — not just of eyes, but of spirit."
  },
  {
    "name": "Elnath",
    "x": -2.4,
    "y": -0.6,
    "z": -1.1,
    "dist": 131,
    "type": "B7III",
    "ra": 81.5729,
    "dec": 28.6075,
    "temperature": 13200,
    "radius": 4.2,
    "mass": 3.4,
    "luminosity": 700,
    "exoplanets": [],
    "description": "Elnath is the horn of Taurus, pointed toward the heart of the sky. It gleams with an icy blue fire, a spear of starlight thrust toward eternity."
  }
]